Metadata-Version: 2.4
Name: iflow-mcp_phone-mcp
Version: 0.3.6
Summary: A phone control plugin for MCP that allows you to control your Android phone through ADB commands to connect any human
Project-URL: Homepage, https://github.com/hao-cyber/phone-mcp
Project-URL: Repository, https://github.com/hao-cyber/phone-mcp
Author-email: hao <hao@hao.com>
License: Apache-2.0
License-File: LICENSE
Keywords: adb,android,mcp,phone
Classifier: License :: OSI Approved :: Apache Software License
Classifier: Operating System :: OS Independent
Classifier: Programming Language :: Python :: 3
Requires-Python: >=3.7
Requires-Dist: aiohttp>=3.8.0
Requires-Dist: asyncio>=3.4.3
Requires-Dist: mcp>=1.6.0
Requires-Dist: pypinyin>=0.54.0
